mux2x1.v
`timescale 1ns/1ps

// 2-bit 2:1 multiplexer
module mux2x1 (
    input wire [1:0] in0,
    input wire [1:0] in1,
    input wire sel,
    output wire [1:0] out
);

    assign out = sel ? in1 : in0;

endmodule

alu.v
`timescale 1ns/1ps

// 2-bit ALU
// sel = 0 -> addition
// sel = 1 -> subtraction
module alu (
    input wire [1:0] a,
    input wire [1:0] b,
    input wire sel,
    output reg [1:0] result
);

    always @(*) begin
        case (sel)
            1'b0: result = a + b;
            1'b1: result = a - b;
            default: result = 2'b00;
        endcase
    end

endmodule

counter.v
`timescale 1ns/1ps

// 4-bit synchronous up counter with synchronous reset
module counter (
    input wire clk,
    input wire rst,
    output reg [3:0] count
);

    always @(posedge clk) begin
        if (rst)
            count <= 4'd0;
        else
            count <= count + 1'b1;
    end

endmodule

mini_soc.v
`timescale 1ns/1ps

// Mini-SoC integrating:
// 1. 4-bit Counter
// 2. 2-bit ALU
// 3. 2:1 MUX

module mini_soc (
    input clk,
    input rst,
    input alu_sel,
    input mux_sel,
    output [1:0] soc_out
);

    wire [3:0] count;
    wire [1:0] alu_out;

    // Counter IP
    counter u_counter (
        .clk(clk),
        .rst(rst),
        .count(count)
    );

    // ALU IP
    // Upper 2 bits of counter -> A
    // Lower 2 bits of counter -> B
    alu u_alu (
        .a(count[3:2]),
        .b(count[1:0]),
        .sel(alu_sel),
        .result(alu_out)
    );

    // MUX IP
    // mux_sel = 0 -> counter MSBs
    // mux_sel = 1 -> ALU output
    mux2x1 u_mux (
        .in0(count[3:2]),
        .in1(alu_out),
        .sel(mux_sel),
        .out(soc_out)
    );

endmodule

mini_soc_tb.v
`timescale 1ns/1ps

module mini_soc_tb;

    reg clk = 0;
    reg rst = 1;
    reg alu_sel = 0;
    reg mux_sel = 0;

    wire [1:0] soc_out;

    // 10 ns clock period
    always #5 clk = ~clk;

    // Instantiate Mini-SoC
    mini_soc dut (
        .clk(clk),
        .rst(rst),
        .alu_sel(alu_sel),
        .mux_sel(mux_sel),
        .soc_out(soc_out)
    );

    initial begin

        // Create waveform file
        $dumpfile("dump.vcd");
        $dumpvars(0, mini_soc_tb);

        // Keep reset active initially
        #10 rst = 0;

        // Change ALU to subtraction
        #20 alu_sel = 1;

        // Select ALU output through MUX
        #30 mux_sel = 1;

        // Change ALU back to addition
        #40 alu_sel = 0;

        // Select counter MSBs through MUX
        #20 mux_sel = 0;

        // Finish simulation
        #50 $finish;

    end

endmodule

dump.vcd
$version Generated by VerilatedVcd $end
$timescale 1ps $end

 $scope module TOP $end
  $scope module mini_soc_tb $end
   $var wire  1 ( alu_sel $end
   $var wire  1 & clk $end
   $var wire  1 ) mux_sel $end
   $var wire  1 ' rst $end
   $var wire  2 * soc_out [1:0] $end
   $scope module dut $end
    $var wire  2 + alu_out [1:0] $end
    $var wire  1 ( alu_sel $end
    $var wire  1 & clk $end
    $var wire  4 # count [3:0] $end
    $var wire  1 ) mux_sel $end
    $var wire  1 ' rst $end
    $var wire  2 * soc_out [1:0] $end
    $scope module u_alu $end
     $var wire  2 $ a [1:0] $end
     $var wire  2 % b [1:0] $end
     $var wire  2 + result [1:0] $end
     $var wire  1 ( sel $end
    $upscope $end
    $scope module u_counter $end
     $var wire  1 & clk $end
     $var wire  4 # count [3:0] $end
     $var wire  1 ' rst $end
    $upscope $end
    $scope module u_mux $end
     $var wire  2 $ in0 [1:0] $end
     $var wire  2 + in1 [1:0] $end
     $var wire  2 * out [1:0] $end
     $var wire  1 ) sel $end
    $upscope $end
   $upscope $end
  $upscope $end
 $upscope $end
$enddefinitions $end


#0
b0000 #
b00 $
b00 %
0&
1'
0(
0)
b00 *
b00 +
#5000
1&
#10000
0&
0'
#15000
b0001 #
b01 %
1&
b01 +
#20000
0&
#25000
b0010 #
b10 %
1&
b10 +
#30000
0&
1(
#35000
b0011 #
b11 %
1&
b01 +
#40000
0&
#45000
b0100 #
b01 $
b00 %
1&
b01 *
#50000
0&
#55000
b0101 #
b01 %
1&
b00 +
#60000
0&
1)
b00 *
#65000
b0110 #
b10 %
1&
b11 *
b11 +
#70000
0&
#75000
b0111 #
b11 %
1&
b10 *
b10 +
#80000
0&
#85000
b1000 #
b10 $
b00 %
1&
#90000
0&
#95000
b1001 #
b01 %
1&
b01 *
b01 +
#100000
0&
0(
b11 *
b11 +
#105000
b1010 #
b10 %
1&
b00 *
b00 +
#110000
0&
#115000
b1011 #
b11 %
1&
b01 *
b01 +
#120000
0&
0)
b10 *
#125000
b1100 #
b11 $
b00 %
1&
b11 *
b11 +
#130000
0&
#135000
b1101 #
b01 %
1&
b00 +
#140000
0&
#145000
b1110 #
b10 %
1&
b01 +
#150000
0&
#155000
b1111 #
b11 %
1&
b10 +
#160000
0&
#165000
b0000 #
b00 $
b00 %
1&
b00 *
b00 +
